pyalux
