Metadata-Version: 1.0
Name: pyalux
Version: 0.3
Summary: unofficial api for alux
Home-page: https://github.com/JarbasAl/pyalux
Author: jarbasAI
Author-email: jarbasai@mailfence.com
License: MIT
Platform: UNKNOWN
